pychlorinator/__init__.py
pychlorinator/chlorinator.py
pychlorinator/chlorinator_parsers.py
pychlorinator/halo_parsers.py
pychlorinator/halochlorinator.py
pychlorinator-0.2.13.dist-info/LICENSE
pychlorinator-0.2.13.dist-info/METADATA
pychlorinator-0.2.13.dist-info/WHEEL
pychlorinator-0.2.13.dist-info/RECORD
