Metadata-Version: 2.1
Name: pychlorinator
Version: 0.2.13
Summary: 
Home-page: https://github.com/pbutterworth/pychlorinator
Author: pbutterworth
Author-email: 3683210+pbutterworth@users.noreply.github.com
Requires-Python: >=3.8,<4.0
Classifier: Programming Language :: Python :: 3
Classifier: Programming Language :: Python :: 3.8
Classifier: Programming Language :: Python :: 3.9
Classifier: Programming Language :: Python :: 3.10
Classifier: Programming Language :: Python :: 3.11
Classifier: Programming Language :: Python :: 3.12
Requires-Dist: bleak (>=0.19.0)
Requires-Dist: pycryptodome (>=3.17,<4.0)
Project-URL: Repository, https://github.com/pbutterworth/pychlorinator
